finviz/__init__.py
finviz/config.py
finviz/main_func.py
finviz/portfolio.py
finviz/screener.py
finviz/helper_functions/__init__.py
finviz/helper_functions/display_functions.py
finviz/helper_functions/error_handling.py
finviz/helper_functions/request_functions.py
finviz/helper_functions/save_data.py
finviz/helper_functions/scraper_functions.py
finviz/tests/conftest.py
finviz/tests/test_integration.py
finviz/tests/test_screener.py
finviz/tests/test_stock.py
finviz-2.0.0.dist-info/licenses/LICENSE
finviz-2.0.0.dist-info/METADATA
finviz-2.0.0.dist-info/WHEEL
finviz-2.0.0.dist-info/top_level.txt
finviz-2.0.0.dist-info/RECORD
