Metadata-Version: 2.4
Name: finviz
Version: 2.0.0
Summary: Unofficial Python API for FinViz - retrieve stock data, screener results, and financial information
Author-email: Mario Stoev <mariostoev@users.noreply.github.com>
Maintainer-email: Mario Stoev <mariostoev@users.noreply.github.com>
License: MIT
Project-URL: Homepage, https://github.com/mariostoev/finviz
Project-URL: Documentation, https://github.com/mariostoev/finviz#readme
Project-URL: Repository, https://github.com/mariostoev/finviz.git
Project-URL: Issues, https://github.com/mariostoev/finviz/issues
Project-URL: Changelog, https://github.com/mariostoev/finviz/blob/main/CHANGELOG.md
Keywords: finviz,finance,stocks,screener,trading,investing,data
Classifier: Development Status :: 4 - Beta
Classifier: Intended Audience :: Developers
Classifier: Intended Audience :: Financial and Insurance Industry
Classifier: License :: OSI Approved :: MIT License
Classifier: Operating System :: OS Independent
Classifier: Programming Language :: Python :: 3
Classifier: Programming Language :: Python :: 3.10
Classifier: Programming Language :: Python :: 3.11
Classifier: Programming Language :: Python :: 3.12
Classifier: Topic :: Office/Business :: Financial :: Investment
Classifier: Topic :: Software Development :: Libraries :: Python Modules
Requires-Python: >=3.10
License-File: LICENSE
Requires-Dist: lxml>=4.9.0
Requires-Dist: requests>=2.28.0
Requires-Dist: aiohttp>=3.8.0
Requires-Dist: cssselect>=1.2.0
Requires-Dist: tqdm>=4.64.0
Requires-Dist: tenacity>=8.0.0
Provides-Extra: dev
Requires-Dist: pytest>=7.0.0; extra == "dev"
Requires-Dist: pytest-asyncio>=0.21.0; extra == "dev"
Requires-Dist: ruff>=0.1.0; extra == "dev"
Requires-Dist: mypy>=1.0.0; extra == "dev"
Requires-Dist: types-requests>=2.28.0; extra == "dev"
Requires-Dist: responses>=0.23.0; extra == "dev"
Dynamic: license-file
